event_interface/__init__.py
st_textnav_8/__init__.py
st_textnav_8/frontend/build/asset-manifest.json
st_textnav_8/frontend/build/bootstrap.min.css
st_textnav_8/frontend/build/index.html
st_textnav_8/frontend/build/precache-manifest.f9e97a579f4bd79d02fd3a93d12c5d4f.js
st_textnav_8/frontend/build/service-worker.js
st_textnav_8/frontend/build/static/js/2.f05f6112.chunk.js
st_textnav_8/frontend/build/static/js/2.f05f6112.chunk.js.LICENSE.txt
st_textnav_8/frontend/build/static/js/2.f05f6112.chunk.js.map
st_textnav_8/frontend/build/static/js/main.ecab78f7.chunk.js
st_textnav_8/frontend/build/static/js/main.ecab78f7.chunk.js.map
st_textnav_8/frontend/build/static/js/runtime-main.44d30fc2.js
st_textnav_8/frontend/build/static/js/runtime-main.44d30fc2.js.map
st_textnav_8-0.0.1.dist-info/LICENSE
st_textnav_8-0.0.1.dist-info/METADATA
st_textnav_8-0.0.1.dist-info/WHEEL
st_textnav_8-0.0.1.dist-info/top_level.txt
st_textnav_8-0.0.1.dist-info/RECORD
